blackbox_gradient_sensing/__init__.py
blackbox_gradient_sensing/bgs.py
blackbox_gradient_sensing-0.4.21.dist-info/METADATA
blackbox_gradient_sensing-0.4.21.dist-info/WHEEL
blackbox_gradient_sensing-0.4.21.dist-info/licenses/LICENSE
blackbox_gradient_sensing-0.4.21.dist-info/RECORD
