Metadata-Version: 2.4
Name: blackbox-gradient-sensing
Version: 0.4.21
Summary: Blackbox Gradient Sensing
Project-URL: Homepage, https://pypi.org/project/blackbox-gradient-sensing/
Project-URL: Repository, https://github.com/lucidrains/blackbox-gradient-sensing
Author-email: Phil Wang <lucidrains@gmail.com>
License: MIT License
License-File: LICENSE
Keywords: artificial intelligence,deep learning,evolutionary strategies,genetic algorithms
Classifier: Development Status :: 4 - Beta
Classifier: Intended Audience :: Developers
Classifier: License :: OSI Approved :: MIT License
Classifier: Programming Language :: Python :: 3.8
Classifier: Topic :: Scientific/Engineering :: Artificial Intelligence
Requires-Python: >=3.8
Requires-Dist: accelerate
Requires-Dist: einops>=0.8.0
Requires-Dist: einx>=0.3.0
Requires-Dist: ema-pytorch
Requires-Dist: torch>=2.4
Requires-Dist: tqdm
Provides-Extra: examples
Requires-Dist: numpy; extra == 'examples'
Requires-Dist: tqdm; extra == 'examples'
